{"web":{"auth_uri":"https://accounts.google.com/o/oauth2/auth","client_secret":"cbPyjKWz6OdSjZq7zhl1tkPo","token_uri":"https://accounts.google.com/o/oauth2/token","client_email":"283664360743-6iv1j2bh3v82q0sdkcnplti35gnsh11t@developer.gserviceaccount.com","redirect_uris":["http://localhost:8008","http://ec2-54-68-82-186.us-west-2.compute.amazonaws.com"],"client_x509_cert_url":"https://www.googleapis.com/robot/v1/metadata/x509/283664360743-6iv1j2bh3v82q0sdkcnplti35gnsh11t@developer.gserviceaccount.com","client_id":"283664360743-6iv1j2bh3v82q0sdkcnplti35gnsh11t.apps.googleusercontent.com","auth_provider_x509_cert_url":"https://www.googleapis.com/oauth2/v1/certs","javascript_origins":["https://www.example.com"]}}